smcleaner/__init__.py
smcleaner/__main__.py
smcleaner/main.py
smcleaner-0.1.0b0.dist-info/LICENSE
smcleaner-0.1.0b0.dist-info/METADATA
smcleaner-0.1.0b0.dist-info/WHEEL
smcleaner-0.1.0b0.dist-info/entry_points.txt
smcleaner-0.1.0b0.dist-info/RECORD
