Metadata-Version: 2.1
Name: smcleaner
Version: 0.1.0b0
Summary: A tool to remove inappropriate content from your social media accounts.
License: MIT
Author: Denis Kazakov
Author-email: denis@kazakov.ru.net
Requires-Python: >=3.12,<4.0
Classifier: License :: OSI Approved :: MIT License
Classifier: Programming Language :: Python :: 3
Requires-Dist: typer[all] (>=0.12.3,<0.13.0)
